nco.v
module nco(
	clk,
	rst,
	phase,		//Начальная фаза
	freq_res,	//Частота сигнала (инкремент фазового аккумулятора)
	out
	);

input clk, rst;
input [5:0] freq_res;
input [7:0] phase;
reg [7:0] prev_phase = 0;
reg change_phase = 0;
output reg [7:0] out;

reg [5:0] phase_inc = 6'h1;
reg [7:0] phase_acc = 0;

parameter LUT_SIZE = 64;
reg [6:0] lut [0:LUT_SIZE-1];

always @(posedge clk) begin
	if (rst) begin
		prev_phase = 0;
		phase_inc = 6'h1;
		phase_acc = 0;
		change_phase = 0;
		out = 0;
		lut[0] = 7'h00;
		lut[1] = 7'h03;
		lut[2] = 7'h06;
		lut[3] = 7'h09;
		lut[4] = 7'h0C;
		lut[5] = 7'h0F;
		lut[6] = 7'h12;
		lut[7] = 7'h16;
		lut[8] = 7'h19;
		lut[9] = 7'h1C;
		lut[10] = 7'h1F;
		lut[11] = 7'h22;
		lut[12] = 7'h25;
		lut[13] = 7'h28;
		lut[14] = 7'h2B;
		lut[15] = 7'h2E;
		lut[16] = 7'h31;
		lut[17] = 7'h34;
		lut[18] = 7'h37;
		lut[19] = 7'h39;
		lut[20] = 7'h3C;
		lut[21] = 7'h3F;
		lut[22] = 7'h42;
		lut[23] = 7'h44;
		lut[24] = 7'h47;
		lut[25] = 7'h4A;
		lut[26] = 7'h4C;
		lut[27] = 7'h4F;
		lut[28] = 7'h51;
		lut[29] = 7'h54;
		lut[30] = 7'h56;
		lut[31] = 7'h58;
		lut[32] = 7'h5A;
		lut[33] = 7'h5D;
		lut[34] = 7'h5F;
		lut[35] = 7'h61;
		lut[36] = 7'h63;
		lut[37] = 7'h65;
		lut[38] = 7'h67;
		lut[39] = 7'h68;
		lut[40] = 7'h6A;
		lut[41] = 7'h6C;
		lut[42] = 7'h6D;
		lut[43] = 7'h6F;
		lut[44] = 7'h71;
		lut[45] = 7'h72;
		lut[46] = 7'h73;
		lut[47] = 7'h75;
		lut[48] = 7'h76;
		lut[49] = 7'h77;
		lut[50] = 7'h78;
		lut[51] = 7'h79;
		lut[52] = 7'h7A;
		lut[53] = 7'h7B;
		lut[54] = 7'h7B;
		lut[55] = 7'h7C;
		lut[56] = 7'h7D;
		lut[57] = 7'h7D;
		lut[58] = 7'h7E;
		lut[59] = 7'h7E;
		lut[60] = 7'h7E;
		lut[61] = 7'h7E;
		lut[62] = 7'h7E;
		lut[63] = 7'h7F;
	end
	else begin
		// Forming sin with 1 clk latency
		if (phase_acc[7:6] == 2'b00) begin
			out = {1'b1,lut[phase_acc[5:0]]};
		end
		if (phase_acc[7:6] == 2'b01) begin
			out = {1'b1,lut[~phase_acc[5:0]]};
		end
		if (phase_acc[7:6] == 2'b10) begin
			out = {1'b0,~lut[phase_acc[5:0]]};
		end
		if (phase_acc[7:6] == 2'b11) begin
			out = {1'b0,~lut[~phase_acc[5:0]]};
		end
		phase_inc = freq_res;
		// Changing phase event with 3 clk latency 
		prev_phase <= phase;
		if (phase != prev_phase) begin
			change_phase <= 1'b1;
		end
		if (change_phase) begin
			phase_acc <= prev_phase;
			change_phase <= 1'b0;
		end
		else begin
			phase_acc = phase_acc + {2'b0,phase_inc};
		end
	end
end

endmodule

nco_tb.v
`include "nco.v"
`timescale 1ns / 1ps

module nco_tb;

reg clk = 0, rst = 0;
reg [7:0] phase = 0;
reg [5:0] freq_res;
wire [7:0] out;

nco nco_inst
	(
	.clk(clk),
	.rst(rst),
	.phase(phase),
	.freq_res(freq_res),
	.out(out)
	);

always
	#2 clk <= ~clk;

initial
	begin
		$dumpfile("out.vcd");
		$dumpvars(0, nco_tb);
		//$monitor("time =%4d   out=%h",$time,out);
		rst = 1'b1;
		freq_res = 1;
		#8
		rst = 1'b0;
		#300
		phase = 8'b00100011;
		#300
		phase = 8'b00001111;
		#1200
		freq_res = 6'b111101;
		#1200
		freq_res = 6'b001111;
		#1200
		freq_res = 6'b011111;
		#400
		phase = 8'b00010011;
		#1200
		$finish;
	end

endmodule

out.vcd
$date
	Thu Apr 18 10:30:46 2019
$end
$version
	Icarus Verilog
$end
$timescale
	1ps
$end
$scope module nco_tb $end
$var wire 8 ! out [7:0] $end
$var reg 1 " clk $end
$var reg 6 # freq_res [5:0] $end
$var reg 8 $ phase [7:0] $end
$var reg 1 % rst $end
$scope module nco_inst $end
$var wire 1 " clk $end
$var wire 6 & freq_res [5:0] $end
$var wire 8 ' phase [7:0] $end
$var wire 1 % rst $end
$var reg 1 ( change_phase $end
$var reg 8 ) out [7:0] $end
$var reg 8 * phase_acc [7:0] $end
$var reg 6 + phase_inc [5:0] $end
$var reg 8 , prev_phase [7:0] $end
$upscope $end
$upscope $end
$enddefinitions $end
#0
$dumpvars
b0 ,
b1 +
b0 *
bx )
0(
b0 '
b1 &
1%
b0 $
b1 #
0"
bx !
$end
#2000
b0 !
b0 )
1"
#4000
0"
#6000
1"
#8000
0"
0%
#10000
b1 *
b10000000 !
b10000000 )
1"
#12000
0"
#14000
b10 *
b10000011 !
b10000011 )
1"
#16000
0"
#18000
b11 *
b10000110 !
b10000110 )
1"
#20000
0"
#22000
b100 *
b10001001 !
b10001001 )
1"
#24000
0"
#26000
b101 *
b10001100 !
b10001100 )
1"
#28000
0"
#30000
b110 *
b10001111 !
b10001111 )
1"
#32000
0"
#34000
b111 *
b10010010 !
b10010010 )
1"
#36000
0"
#38000
b1000 *
b10010110 !
b10010110 )
1"
#40000
0"
#42000
b1001 *
b10011001 !
b10011001 )
1"
#44000
0"
#46000
b1010 *
b10011100 !
b10011100 )
1"
#48000
0"
#50000
b1011 *
b10011111 !
b10011111 )
1"
#52000
0"
#54000
b1100 *
b10100010 !
b10100010 )
1"
#56000
0"
#58000
b1101 *
b10100101 !
b10100101 )
1"
#60000
0"
#62000
b1110 *
b10101000 !
b10101000 )
1"
#64000
0"
#66000
b1111 *
b10101011 !
b10101011 )
1"
#68000
0"
#70000
b10000 *
b10101110 !
b10101110 )
1"
#72000
0"
#74000
b10001 *
b10110001 !
b10110001 )
1"
#76000
0"
#78000
b10010 *
b10110100 !
b10110100 )
1"
#80000
0"
#82000
b10011 *
b10110111 !
b10110111 )
1"
#84000
0"
#86000
b10100 *
b10111001 !
b10111001 )
1"
#88000
0"
#90000
b10101 *
b10111100 !
b10111100 )
1"
#92000
0"
#94000
b10110 *
b10111111 !
b10111111 )
1"
#96000
0"
#98000
b10111 *
b11000010 !
b11000010 )
1"
#100000
0"
#102000
b11000 *
b11000100 !
b11000100 )
1"
#104000
0"
#106000
b11001 *
b11000111 !
b11000111 )
1"
#108000
0"
#110000
b11010 *
b11001010 !
b11001010 )
1"
#112000
0"
#114000
b11011 *
b11001100 !
b11001100 )
1"
#116000
0"
#118000
b11100 *
b11001111 !
b11001111 )
1"
#120000
0"
#122000
b11101 *
b11010001 !
b11010001 )
1"
#124000
0"
#126000
b11110 *
b11010100 !
b11010100 )
1"
#128000
0"
#130000
b11111 *
b11010110 !
b11010110 )
1"
#132000
0"
#134000
b100000 *
b11011000 !
b11011000 )
1"
#136000
0"
#138000
b100001 *
b11011010 !
b11011010 )
1"
#140000
0"
#142000
b100010 *
b11011101 !
b11011101 )
1"
#144000
0"
#146000
b100011 *
b11011111 !
b11011111 )
1"
#148000
0"
#150000
b100100 *
b11100001 !
b11100001 )
1"
#152000
0"
#154000
b100101 *
b11100011 !
b11100011 )
1"
#156000
0"
#158000
b100110 *
b11100101 !
b11100101 )
1"
#160000
0"
#162000
b100111 *
b11100111 !
b11100111 )
1"
#164000
0"
#166000
b101000 *
b11101000 !
b11101000 )
1"
#168000
0"
#170000
b101001 *
b11101010 !
b11101010 )
1"
#172000
0"
#174000
b101010 *
b11101100 !
b11101100 )
1"
#176000
0"
#178000
b101011 *
b11101101 !
b11101101 )
1"
#180000
0"
#182000
b101100 *
b11101111 !
b11101111 )
1"
#184000
0"
#186000
b101101 *
b11110001 !
b11110001 )
1"
#188000
0"
#190000
b101110 *
b11110010 !
b11110010 )
1"
#192000
0"
#194000
b101111 *
b11110011 !
b11110011 )
1"
#196000
0"
#198000
b110000 *
b11110101 !
b11110101 )
1"
#200000
0"
#202000
b110001 *
b11110110 !
b11110110 )
1"
#204000
0"
#206000
b110010 *
b11110111 !
b11110111 )
1"
#208000
0"
#210000
b110011 *
b11111000 !
b11111000 )
1"
#212000
0"
#214000
b110100 *
b11111001 !
b11111001 )
1"
#216000
0"
#218000
b110101 *
b11111010 !
b11111010 )
1"
#220000
0"
#222000
b110110 *
b11111011 !
b11111011 )
1"
#224000
0"
#226000
b110111 *
1"
#228000
0"
#230000
b111000 *
b11111100 !
b11111100 )
1"
#232000
0"
#234000
b111001 *
b11111101 !
b11111101 )
1"
#236000
0"
#238000
b111010 *
1"
#240000
0"
#242000
b111011 *
b11111110 !
b11111110 )
1"
#244000
0"
#246000
b111100 *
1"
#248000
0"
#250000
b111101 *
1"
#252000
0"
#254000
b111110 *
1"
#256000
0"
#258000
b111111 *
1"
#260000
0"
#262000
b1000000 *
b11111111 !
b11111111 )
1"
#264000
0"
#266000
b1000001 *
1"
#268000
0"
#270000
b1000010 *
b11111110 !
b11111110 )
1"
#272000
0"
#274000
b1000011 *
1"
#276000
0"
#278000
b1000100 *
1"
#280000
0"
#282000
b1000101 *
1"
#284000
0"
#286000
b1000110 *
1"
#288000
0"
#290000
b1000111 *
b11111101 !
b11111101 )
1"
#292000
0"
#294000
b1001000 *
1"
#296000
0"
#298000
b1001001 *
b11111100 !
b11111100 )
1"
#300000
0"
#302000
b1001010 *
b11111011 !
b11111011 )
1"
#304000
0"
#306000
b1001011 *
1"
#308000
0"
b100011 $
b100011 '
#310000
1(
b100011 ,
b1001100 *
b11111010 !
b11111010 )
1"
#312000
0"
#314000
0(
b100011 *
b11111001 !
b11111001 )
1"
#316000
0"
#318000
b100100 *
b11100001 !
b11100001 )
1"
#320000
0"
#322000
b100101 *
b11100011 !
b11100011 )
1"
#324000
0"
#326000
b100110 *
b11100101 !
b11100101 )
1"
#328000
0"
#330000
b100111 *
b11100111 !
b11100111 )
1"
#332000
0"
#334000
b101000 *
b11101000 !
b11101000 )
1"
#336000
0"
#338000
b101001 *
b11101010 !
b11101010 )
1"
#340000
0"
#342000
b101010 *
b11101100 !
b11101100 )
1"
#344000
0"
#346000
b101011 *
b11101101 !
b11101101 )
1"
#348000
0"
#350000
b101100 *
b11101111 !
b11101111 )
1"
#352000
0"
#354000
b101101 *
b11110001 !
b11110001 )
1"
#356000
0"
#358000
b101110 *
b11110010 !
b11110010 )
1"
#360000
0"
#362000
b101111 *
b11110011 !
b11110011 )
1"
#364000
0"
#366000
b110000 *
b11110101 !
b11110101 )
1"
#368000
0"
#370000
b110001 *
b11110110 !
b11110110 )
1"
#372000
0"
#374000
b110010 *
b11110111 !
b11110111 )
1"
#376000
0"
#378000
b110011 *
b11111000 !
b11111000 )
1"
#380000
0"
#382000
b110100 *
b11111001 !
b11111001 )
1"
#384000
0"
#386000
b110101 *
b11111010 !
b11111010 )
1"
#388000
0"
#390000
b110110 *
b11111011 !
b11111011 )
1"
#392000
0"
#394000
b110111 *
1"
#396000
0"
#398000
b111000 *
b11111100 !
b11111100 )
1"
#400000
0"
#402000
b111001 *
b11111101 !
b11111101 )
1"
#404000
0"
#406000
b111010 *
1"
#408000
0"
#410000
b111011 *
b11111110 !
b11111110 )
1"
#412000
0"
#414000
b111100 *
1"
#416000
0"
#418000
b111101 *
1"
#420000
0"
#422000
b111110 *
1"
#424000
0"
#426000
b111111 *
1"
#428000
0"
#430000
b1000000 *
b11111111 !
b11111111 )
1"
#432000
0"
#434000
b1000001 *
1"
#436000
0"
#438000
b1000010 *
b11111110 !
b11111110 )
1"
#440000
0"
#442000
b1000011 *
1"
#444000
0"
#446000
b1000100 *
1"
#448000
0"
#450000
b1000101 *
1"
#452000
0"
#454000
b1000110 *
1"
#456000
0"
#458000
b1000111 *
b11111101 !
b11111101 )
1"
#460000
0"
#462000
b1001000 *
1"
#464000
0"
#466000
b1001001 *
b11111100 !
b11111100 )
1"
#468000
0"
#470000
b1001010 *
b11111011 !
b11111011 )
1"
#472000
0"
#474000
b1001011 *
1"
#476000
0"
#478000
b1001100 *
b11111010 !
b11111010 )
1"
#480000
0"
#482000
b1001101 *
b11111001 !
b11111001 )
1"
#484000
0"
#486000
b1001110 *
b11111000 !
b11111000 )
1"
#488000
0"
#490000
b1001111 *
b11110111 !
b11110111 )
1"
#492000
0"
#494000
b1010000 *
b11110110 !
b11110110 )
1"
#496000
0"
#498000
b1010001 *
b11110101 !
b11110101 )
1"
#500000
0"
#502000
b1010010 *
b11110011 !
b11110011 )
1"
#504000
0"
#506000
b1010011 *
b11110010 !
b11110010 )
1"
#508000
0"
#510000
b1010100 *
b11110001 !
b11110001 )
1"
#512000
0"
#514000
b1010101 *
b11101111 !
b11101111 )
1"
#516000
0"
#518000
b1010110 *
b11101101 !
b11101101 )
1"
#520000
0"
#522000
b1010111 *
b11101100 !
b11101100 )
1"
#524000
0"
#526000
b1011000 *
b11101010 !
b11101010 )
1"
#528000
0"
#530000
b1011001 *
b11101000 !
b11101000 )
1"
#532000
0"
#534000
b1011010 *
b11100111 !
b11100111 )
1"
#536000
0"
#538000
b1011011 *
b11100101 !
b11100101 )
1"
#540000
0"
#542000
b1011100 *
b11100011 !
b11100011 )
1"
#544000
0"
#546000
b1011101 *
b11100001 !
b11100001 )
1"
#548000
0"
#550000
b1011110 *
b11011111 !
b11011111 )
1"
#552000
0"
#554000
b1011111 *
b11011101 !
b11011101 )
1"
#556000
0"
#558000
b1100000 *
b11011010 !
b11011010 )
1"
#560000
0"
#562000
b1100001 *
b11011000 !
b11011000 )
1"
#564000
0"
#566000
b1100010 *
b11010110 !
b11010110 )
1"
#568000
0"
#570000
b1100011 *
b11010100 !
b11010100 )
1"
#572000
0"
#574000
b1100100 *
b11010001 !
b11010001 )
1"
#576000
0"
#578000
b1100101 *
b11001111 !
b11001111 )
1"
#580000
0"
#582000
b1100110 *
b11001100 !
b11001100 )
1"
#584000
0"
#586000
b1100111 *
b11001010 !
b11001010 )
1"
#588000
0"
#590000
b1101000 *
b11000111 !
b11000111 )
1"
#592000
0"
#594000
b1101001 *
b11000100 !
b11000100 )
1"
#596000
0"
#598000
b1101010 *
b11000010 !
b11000010 )
1"
#600000
0"
#602000
b1101011 *
b10111111 !
b10111111 )
1"
#604000
0"
#606000
b1101100 *
b10111100 !
b10111100 )
1"
#608000
0"
b1111 $
b1111 '
#610000
1(
b1111 ,
b1101101 *
b10111001 !
b10111001 )
1"
#612000
0"
#614000
0(
b1111 *
b10110111 !
b10110111 )
1"
#616000
0"
#618000
b10000 *
b10101110 !
b10101110 )
1"
#620000
0"
#622000
b10001 *
b10110001 !
b10110001 )
1"
#624000
0"
#626000
b10010 *
b10110100 !
b10110100 )
1"
#628000
0"
#630000
b10011 *
b10110111 !
b10110111 )
1"
#632000
0"
#634000
b10100 *
b10111001 !
b10111001 )
1"
#636000
0"
#638000
b10101 *
b10111100 !
b10111100 )
1"
#640000
0"
#642000
b10110 *
b10111111 !
b10111111 )
1"
#644000
0"
#646000
b10111 *
b11000010 !
b11000010 )
1"
#648000
0"
#650000
b11000 *
b11000100 !
b11000100 )
1"
#652000
0"
#654000
b11001 *
b11000111 !
b11000111 )
1"
#656000
0"
#658000
b11010 *
b11001010 !
b11001010 )
1"
#660000
0"
#662000
b11011 *
b11001100 !
b11001100 )
1"
#664000
0"
#666000
b11100 *
b11001111 !
b11001111 )
1"
#668000
0"
#670000
b11101 *
b11010001 !
b11010001 )
1"
#672000
0"
#674000
b11110 *
b11010100 !
b11010100 )
1"
#676000
0"
#678000
b11111 *
b11010110 !
b11010110 )
1"
#680000
0"
#682000
b100000 *
b11011000 !
b11011000 )
1"
#684000
0"
#686000
b100001 *
b11011010 !
b11011010 )
1"
#688000
0"
#690000
b100010 *
b11011101 !
b11011101 )
1"
#692000
0"
#694000
b100011 *
b11011111 !
b11011111 )
1"
#696000
0"
#698000
b100100 *
b11100001 !
b11100001 )
1"
#700000
0"
#702000
b100101 *
b11100011 !
b11100011 )
1"
#704000
0"
#706000
b100110 *
b11100101 !
b11100101 )
1"
#708000
0"
#710000
b100111 *
b11100111 !
b11100111 )
1"
#712000
0"
#714000
b101000 *
b11101000 !
b11101000 )
1"
#716000
0"
#718000
b101001 *
b11101010 !
b11101010 )
1"
#720000
0"
#722000
b101010 *
b11101100 !
b11101100 )
1"
#724000
0"
#726000
b101011 *
b11101101 !
b11101101 )
1"
#728000
0"
#730000
b101100 *
b11101111 !
b11101111 )
1"
#732000
0"
#734000
b101101 *
b11110001 !
b11110001 )
1"
#736000
0"
#738000
b101110 *
b11110010 !
b11110010 )
1"
#740000
0"
#742000
b101111 *
b11110011 !
b11110011 )
1"
#744000
0"
#746000
b110000 *
b11110101 !
b11110101 )
1"
#748000
0"
#750000
b110001 *
b11110110 !
b11110110 )
1"
#752000
0"
#754000
b110010 *
b11110111 !
b11110111 )
1"
#756000
0"
#758000
b110011 *
b11111000 !
b11111000 )
1"
#760000
0"
#762000
b110100 *
b11111001 !
b11111001 )
1"
#764000
0"
#766000
b110101 *
b11111010 !
b11111010 )
1"
#768000
0"
#770000
b110110 *
b11111011 !
b11111011 )
1"
#772000
0"
#774000
b110111 *
1"
#776000
0"
#778000
b111000 *
b11111100 !
b11111100 )
1"
#780000
0"
#782000
b111001 *
b11111101 !
b11111101 )
1"
#784000
0"
#786000
b111010 *
1"
#788000
0"
#790000
b111011 *
b11111110 !
b11111110 )
1"
#792000
0"
#794000
b111100 *
1"
#796000
0"
#798000
b111101 *
1"
#800000
0"
#802000
b111110 *
1"
#804000
0"
#806000
b111111 *
1"
#808000
0"
#810000
b1000000 *
b11111111 !
b11111111 )
1"
#812000
0"
#814000
b1000001 *
1"
#816000
0"
#818000
b1000010 *
b11111110 !
b11111110 )
1"
#820000
0"
#822000
b1000011 *
1"
#824000
0"
#826000
b1000100 *
1"
#828000
0"
#830000
b1000101 *
1"
#832000
0"
#834000
b1000110 *
1"
#836000
0"
#838000
b1000111 *
b11111101 !
b11111101 )
1"
#840000
0"
#842000
b1001000 *
1"
#844000
0"
#846000
b1001001 *
b11111100 !
b11111100 )
1"
#848000
0"
#850000
b1001010 *
b11111011 !
b11111011 )
1"
#852000
0"
#854000
b1001011 *
1"
#856000
0"
#858000
b1001100 *
b11111010 !
b11111010 )
1"
#860000
0"
#862000
b1001101 *
b11111001 !
b11111001 )
1"
#864000
0"
#866000
b1001110 *
b11111000 !
b11111000 )
1"
#868000
0"
#870000
b1001111 *
b11110111 !
b11110111 )
1"
#872000
0"
#874000
b1010000 *
b11110110 !
b11110110 )
1"
#876000
0"
#878000
b1010001 *
b11110101 !
b11110101 )
1"
#880000
0"
#882000
b1010010 *
b11110011 !
b11110011 )
1"
#884000
0"
#886000
b1010011 *
b11110010 !
b11110010 )
1"
#888000
0"
#890000
b1010100 *
b11110001 !
b11110001 )
1"
#892000
0"
#894000
b1010101 *
b11101111 !
b11101111 )
1"
#896000
0"
#898000
b1010110 *
b11101101 !
b11101101 )
1"
#900000
0"
#902000
b1010111 *
b11101100 !
b11101100 )
1"
#904000
0"
#906000
b1011000 *
b11101010 !
b11101010 )
1"
#908000
0"
#910000
b1011001 *
b11101000 !
b11101000 )
1"
#912000
0"
#914000
b1011010 *
b11100111 !
b11100111 )
1"
#916000
0"
#918000
b1011011 *
b11100101 !
b11100101 )
1"
#920000
0"
#922000
b1011100 *
b11100011 !
b11100011 )
1"
#924000
0"
#926000
b1011101 *
b11100001 !
b11100001 )
1"
#928000
0"
#930000
b1011110 *
b11011111 !
b11011111 )
1"
#932000
0"
#934000
b1011111 *
b11011101 !
b11011101 )
1"
#936000
0"
#938000
b1100000 *
b11011010 !
b11011010 )
1"
#940000
0"
#942000
b1100001 *
b11011000 !
b11011000 )
1"
#944000
0"
#946000
b1100010 *
b11010110 !
b11010110 )
1"
#948000
0"
#950000
b1100011 *
b11010100 !
b11010100 )
1"
#952000
0"
#954000
b1100100 *
b11010001 !
b11010001 )
1"
#956000
0"
#958000
b1100101 *
b11001111 !
b11001111 )
1"
#960000
0"
#962000
b1100110 *
b11001100 !
b11001100 )
1"
#964000
0"
#966000
b1100111 *
b11001010 !
b11001010 )
1"
#968000
0"
#970000
b1101000 *
b11000111 !
b11000111 )
1"
#972000
0"
#974000
b1101001 *
b11000100 !
b11000100 )
1"
#976000
0"
#978000
b1101010 *
b11000010 !
b11000010 )
1"
#980000
0"
#982000
b1101011 *
b10111111 !
b10111111 )
1"
#984000
0"
#986000
b1101100 *
b10111100 !
b10111100 )
1"
#988000
0"
#990000
b1101101 *
b10111001 !
b10111001 )
1"
#992000
0"
#994000
b1101110 *
b10110111 !
b10110111 )
1"
#996000
0"
#998000
b1101111 *
b10110100 !
b10110100 )
1"
#1000000
0"
#1002000
b1110000 *
b10110001 !
b10110001 )
1"
#1004000
0"
#1006000
b1110001 *
b10101110 !
b10101110 )
1"
#1008000
0"
#1010000
b1110010 *
b10101011 !
b10101011 )
1"
#1012000
0"
#1014000
b1110011 *
b10101000 !
b10101000 )
1"
#1016000
0"
#1018000
b1110100 *
b10100101 !
b10100101 )
1"
#1020000
0"
#1022000
b1110101 *
b10100010 !
b10100010 )
1"
#1024000
0"
#1026000
b1110110 *
b10011111 !
b10011111 )
1"
#1028000
0"
#1030000
b1110111 *
b10011100 !
b10011100 )
1"
#1032000
0"
#1034000
b1111000 *
b10011001 !
b10011001 )
1"
#1036000
0"
#1038000
b1111001 *
b10010110 !
b10010110 )
1"
#1040000
0"
#1042000
b1111010 *
b10010010 !
b10010010 )
1"
#1044000
0"
#1046000
b1111011 *
b10001111 !
b10001111 )
1"
#1048000
0"
#1050000
b1111100 *
b10001100 !
b10001100 )
1"
#1052000
0"
#1054000
b1111101 *
b10001001 !
b10001001 )
1"
#1056000
0"
#1058000
b1111110 *
b10000110 !
b10000110 )
1"
#1060000
0"
#1062000
b1111111 *
b10000011 !
b10000011 )
1"
#1064000
0"
#1066000
b10000000 *
b10000000 !
b10000000 )
1"
#1068000
0"
#1070000
b10000001 *
b1111111 !
b1111111 )
1"
#1072000
0"
#1074000
b10000010 *
b1111100 !
b1111100 )
1"
#1076000
0"
#1078000
b10000011 *
b1111001 !
b1111001 )
1"
#1080000
0"
#1082000
b10000100 *
b1110110 !
b1110110 )
1"
#1084000
0"
#1086000
b10000101 *
b1110011 !
b1110011 )
1"
#1088000
0"
#1090000
b10000110 *
b1110000 !
b1110000 )
1"
#1092000
0"
#1094000
b10000111 *
b1101101 !
b1101101 )
1"
#1096000
0"
#1098000
b10001000 *
b1101001 !
b1101001 )
1"
#1100000
0"
#1102000
b10001001 *
b1100110 !
b1100110 )
1"
#1104000
0"
#1106000
b10001010 *
b1100011 !
b1100011 )
1"
#1108000
0"
#1110000
b10001011 *
b1100000 !
b1100000 )
1"
#1112000
0"
#1114000
b10001100 *
b1011101 !
b1011101 )
1"
#1116000
0"
#1118000
b10001101 *
b1011010 !
b1011010 )
1"
#1120000
0"
#1122000
b10001110 *
b1010111 !
b1010111 )
1"
#1124000
0"
#1126000
b10001111 *
b1010100 !
b1010100 )
1"
#1128000
0"
#1130000
b10010000 *
b1010001 !
b1010001 )
1"
#1132000
0"
#1134000
b10010001 *
b1001110 !
b1001110 )
1"
#1136000
0"
#1138000
b10010010 *
b1001011 !
b1001011 )
1"
#1140000
0"
#1142000
b10010011 *
b1001000 !
b1001000 )
1"
#1144000
0"
#1146000
b10010100 *
b1000110 !
b1000110 )
1"
#1148000
0"
#1150000
b10010101 *
b1000011 !
b1000011 )
1"
#1152000
0"
#1154000
b10010110 *
b1000000 !
b1000000 )
1"
#1156000
0"
#1158000
b10010111 *
b111101 !
b111101 )
1"
#1160000
0"
#1162000
b10011000 *
b111011 !
b111011 )
1"
#1164000
0"
#1166000
b10011001 *
b111000 !
b111000 )
1"
#1168000
0"
#1170000
b10011010 *
b110101 !
b110101 )
1"
#1172000
0"
#1174000
b10011011 *
b110011 !
b110011 )
1"
#1176000
0"
#1178000
b10011100 *
b110000 !
b110000 )
1"
#1180000
0"
#1182000
b10011101 *
b101110 !
b101110 )
1"
#1184000
0"
#1186000
b10011110 *
b101011 !
b101011 )
1"
#1188000
0"
#1190000
b10011111 *
b101001 !
b101001 )
1"
#1192000
0"
#1194000
b10100000 *
b100111 !
b100111 )
1"
#1196000
0"
#1198000
b10100001 *
b100101 !
b100101 )
1"
#1200000
0"
#1202000
b10100010 *
b100010 !
b100010 )
1"
#1204000
0"
#1206000
b10100011 *
b100000 !
b100000 )
1"
#1208000
0"
#1210000
b10100100 *
b11110 !
b11110 )
1"
#1212000
0"
#1214000
b10100101 *
b11100 !
b11100 )
1"
#1216000
0"
#1218000
b10100110 *
b11010 !
b11010 )
1"
#1220000
0"
#1222000
b10100111 *
b11000 !
b11000 )
1"
#1224000
0"
#1226000
b10101000 *
b10111 !
b10111 )
1"
#1228000
0"
#1230000
b10101001 *
b10101 !
b10101 )
1"
#1232000
0"
#1234000
b10101010 *
b10011 !
b10011 )
1"
#1236000
0"
#1238000
b10101011 *
b10010 !
b10010 )
1"
#1240000
0"
#1242000
b10101100 *
b10000 !
b10000 )
1"
#1244000
0"
#1246000
b10101101 *
b1110 !
b1110 )
1"
#1248000
0"
#1250000
b10101110 *
b1101 !
b1101 )
1"
#1252000
0"
#1254000
b10101111 *
b1100 !
b1100 )
1"
#1256000
0"
#1258000
b10110000 *
b1010 !
b1010 )
1"
#1260000
0"
#1262000
b10110001 *
b1001 !
b1001 )
1"
#1264000
0"
#1266000
b10110010 *
b1000 !
b1000 )
1"
#1268000
0"
#1270000
b10110011 *
b111 !
b111 )
1"
#1272000
0"
#1274000
b10110100 *
b110 !
b110 )
1"
#1276000
0"
#1278000
b10110101 *
b101 !
b101 )
1"
#1280000
0"
#1282000
b10110110 *
b100 !
b100 )
1"
#1284000
0"
#1286000
b10110111 *
1"
#1288000
0"
#1290000
b10111000 *
b11 !
b11 )
1"
#1292000
0"
#1294000
b10111001 *
b10 !
b10 )
1"
#1296000
0"
#1298000
b10111010 *
1"
#1300000
0"
#1302000
b10111011 *
b1 !
b1 )
1"
#1304000
0"
#1306000
b10111100 *
1"
#1308000
0"
#1310000
b10111101 *
1"
#1312000
0"
#1314000
b10111110 *
1"
#1316000
0"
#1318000
b10111111 *
1"
#1320000
0"
#1322000
b11000000 *
b0 !
b0 )
1"
#1324000
0"
#1326000
b11000001 *
1"
#1328000
0"
#1330000
b11000010 *
b1 !
b1 )
1"
#1332000
0"
#1334000
b11000011 *
1"
#1336000
0"
#1338000
b11000100 *
1"
#1340000
0"
#1342000
b11000101 *
1"
#1344000
0"
#1346000
b11000110 *
1"
#1348000
0"
#1350000
b11000111 *
b10 !
b10 )
1"
#1352000
0"
#1354000
b11001000 *
1"
#1356000
0"
#1358000
b11001001 *
b11 !
b11 )
1"
#1360000
0"
#1362000
b11001010 *
b100 !
b100 )
1"
#1364000
0"
#1366000
b11001011 *
1"
#1368000
0"
#1370000
b11001100 *
b101 !
b101 )
1"
#1372000
0"
#1374000
b11001101 *
b110 !
b110 )
1"
#1376000
0"
#1378000
b11001110 *
b111 !
b111 )
1"
#1380000
0"
#1382000
b11001111 *
b1000 !
b1000 )
1"
#1384000
0"
#1386000
b11010000 *
b1001 !
b1001 )
1"
#1388000
0"
#1390000
b11010001 *
b1010 !
b1010 )
1"
#1392000
0"
#1394000
b11010010 *
b1100 !
b1100 )
1"
#1396000
0"
#1398000
b11010011 *
b1101 !
b1101 )
1"
#1400000
0"
#1402000
b11010100 *
b1110 !
b1110 )
1"
#1404000
0"
#1406000
b11010101 *
b10000 !
b10000 )
1"
#1408000
0"
#1410000
b11010110 *
b10010 !
b10010 )
1"
#1412000
0"
#1414000
b11010111 *
b10011 !
b10011 )
1"
#1416000
0"
#1418000
b11011000 *
b10101 !
b10101 )
1"
#1420000
0"
#1422000
b11011001 *
b10111 !
b10111 )
1"
#1424000
0"
#1426000
b11011010 *
b11000 !
b11000 )
1"
#1428000
0"
#1430000
b11011011 *
b11010 !
b11010 )
1"
#1432000
0"
#1434000
b11011100 *
b11100 !
b11100 )
1"
#1436000
0"
#1438000
b11011101 *
b11110 !
b11110 )
1"
#1440000
0"
#1442000
b11011110 *
b100000 !
b100000 )
1"
#1444000
0"
#1446000
b11011111 *
b100010 !
b100010 )
1"
#1448000
0"
#1450000
b11100000 *
b100101 !
b100101 )
1"
#1452000
0"
#1454000
b11100001 *
b100111 !
b100111 )
1"
#1456000
0"
#1458000
b11100010 *
b101001 !
b101001 )
1"
#1460000
0"
#1462000
b11100011 *
b101011 !
b101011 )
1"
#1464000
0"
#1466000
b11100100 *
b101110 !
b101110 )
1"
#1468000
0"
#1470000
b11100101 *
b110000 !
b110000 )
1"
#1472000
0"
#1474000
b11100110 *
b110011 !
b110011 )
1"
#1476000
0"
#1478000
b11100111 *
b110101 !
b110101 )
1"
#1480000
0"
#1482000
b11101000 *
b111000 !
b111000 )
1"
#1484000
0"
#1486000
b11101001 *
b111011 !
b111011 )
1"
#1488000
0"
#1490000
b11101010 *
b111101 !
b111101 )
1"
#1492000
0"
#1494000
b11101011 *
b1000000 !
b1000000 )
1"
#1496000
0"
#1498000
b11101100 *
b1000011 !
b1000011 )
1"
#1500000
0"
#1502000
b11101101 *
b1000110 !
b1000110 )
1"
#1504000
0"
#1506000
b11101110 *
b1001000 !
b1001000 )
1"
#1508000
0"
#1510000
b11101111 *
b1001011 !
b1001011 )
1"
#1512000
0"
#1514000
b11110000 *
b1001110 !
b1001110 )
1"
#1516000
0"
#1518000
b11110001 *
b1010001 !
b1010001 )
1"
#1520000
0"
#1522000
b11110010 *
b1010100 !
b1010100 )
1"
#1524000
0"
